{
  "sample_meta": {
    "timestamp": "2026-04-02T10:54:48+08:00",
    "timestamp_unix": 1775098488,
    "host": "node-2",
    "mds_name": "node-2.cephfs.dowhqz",
    "mds_daemon": "mds.node-2.cephfs.dowhqz",
    "cluster": "ceph",
    "tag": "2026-04-02_083803",
    "seq": 411
  },
  "perf_dump": {
    "AsyncMessenger::Worker-0": {
      "msgr_recv_messages": 666920302,
      "msgr_send_messages": 876101155,
      "msgr_recv_bytes": 451485803340,
      "msgr_send_bytes": 830853654891,
      "msgr_created_connections": 31990,
      "msgr_active_connections": 14,
      "msgr_running_total_time": 21863.565745876,
      "msgr_running_send_time": 10632.051913826,
      "msgr_running_recv_time": 19121.119074693,
      "msgr_running_fast_dispatch_time": 1802.430471614,
      "msgr_send_messages_queue_lat": {
        "avgcount": 876089264,
        "sum": 180020.658758984,
        "avgtime": 0.000205482
      },
      "msgr_handle_ack_lat": {
        "avgcount": 1059387461,
        "sum": 157.966659276,
        "avgtime": 1.49e-07
      }
    },
    "AsyncMessenger::Worker-1": {
      "msgr_recv_messages": 514029069,
      "msgr_send_messages": 628239721,
      "msgr_recv_bytes": 675322538849,
      "msgr_send_bytes": 1056042844985,
      "msgr_created_connections": 8187,
      "msgr_active_connections": 17,
      "msgr_running_total_time": 18047.694323565,
      "msgr_running_send_time": 8188.017836469,
      "msgr_running_recv_time": 13357.38505049,
      "msgr_running_fast_dispatch_time": 3173.999490065,
      "msgr_send_messages_queue_lat": {
        "avgcount": 628239580,
        "sum": 541599.294369376,
        "avgtime": 0.00086209
      },
      "msgr_handle_ack_lat": {
        "avgcount": 610315421,
        "sum": 104.483317248,
        "avgtime": 1.71e-07
      }
    },
    "AsyncMessenger::Worker-2": {
      "msgr_recv_messages": 542956463,
      "msgr_send_messages": 685481289,
      "msgr_recv_bytes": 580050595108,
      "msgr_send_bytes": 961282398094,
      "msgr_created_connections": 24482,
      "msgr_active_connections": 15,
      "msgr_running_total_time": 18311.790695573,
      "msgr_running_send_time": 8279.583510569,
      "msgr_running_recv_time": 17240.739959776,
      "msgr_running_fast_dispatch_time": 2579.382991975,
      "msgr_send_messages_queue_lat": {
        "avgcount": 685469208,
        "sum": 389578.627802496,
        "avgtime": 0.000568338
      },
      "msgr_handle_ack_lat": {
        "avgcount": 741758734,
        "sum": 124.940539606,
        "avgtime": 1.68e-07
      }
    },
    "cct": {
      "total_workers": 1,
      "unhealthy_workers": 0
    },
    "finisher-MDSRank": {
      "queue_len": 0,
      "complete_latency": {
        "avgcount": 54653661,
        "sum": 67362.596559699,
        "avgtime": 0.001232535
      }
    },
    "finisher-PurgeQueue": {
      "queue_len": 0,
      "complete_latency": {
        "avgcount": 187243876,
        "sum": 12378.782154662,
        "avgtime": 6.611e-05
      }
    },
    "mds": {
      "request": 1068796006,
      "reply": 1053906452,
      "reply_latency": {
        "avgcount": 1053906452,
        "sum": 5443659.410268631,
        "avgtime": 0.00516522
      },
      "slow_reply": 14,
      "forward": 14889548,
      "dir_fetch": 934122,
      "dir_commit": 69504555,
      "dir_split": 6839,
      "dir_merge": 9743,
      "inodes": 1800942,
      "inodes_top": 1144150,
      "inodes_bottom": 638537,
      "inodes_pin_tail": 18255,
      "inodes_pinned": 166441,
      "inodes_expired": 1379812485,
      "inodes_with_caps": 150590,
      "caps": 150612,
      "subtrees": 45,
      "traverse": 1694432088,
      "traverse_hit": 1129717267,
      "traverse_forward": 5690213,
      "traverse_discover": 572522,
      "traverse_dir_fetch": 855099,
      "traverse_remote_ino": 0,
      "traverse_lock": 19252613,
      "load_cent": 6628235,
      "q": 85,
      "exported": 495079,
      "exported_inodes": 19658626,
      "imported": 509030,
      "imported_inodes": 19873653,
      "openino_dir_fetch": 76929,
      "openino_backtrace_fetch": 84077,
      "openino_peer_discover": 13571421,
      "root_rfiles": 1905206,
      "root_rbytes": 369,
      "root_rsnaps": 0,
      "scrub_backtrace_fetch": 0,
      "scrub_set_tag": 0,
      "scrub_backtrace_repaired": 0,
      "scrub_inotable_repaired": 0,
      "scrub_dir_inodes": 0,
      "scrub_dir_base_inodes": 0,
      "scrub_dirfrag_rstats": 0,
      "scrub_file_inodes": 0,
      "handle_inode_file_caps": 15375,
      "ceph_cap_op_revoke": 26402602,
      "ceph_cap_op_grant": 219426535,
      "ceph_cap_op_trunc": 0,
      "ceph_cap_op_flushsnap_ack": 0,
      "ceph_cap_op_flush_ack": 0,
      "handle_client_caps": 102665566,
      "handle_client_caps_dirty": 5,
      "handle_client_cap_release": 274272,
      "process_request_cap_release": 604230684
    },
    "mds_cache": {
      "num_strays": 1839,
      "num_strays_delayed": 0,
      "num_strays_enqueuing": 0,
      "strays_created": 132948396,
      "strays_enqueued": 132946557,
      "strays_reintegrated": 0,
      "strays_migrated": 0,
      "num_recovering_processing": 0,
      "num_recovering_enqueued": 0,
      "num_recovering_prioritized": 0,
      "recovery_started": 0,
      "recovery_completed": 0,
      "ireq_enqueue_scrub": 0,
      "ireq_exportdir": 496808,
      "ireq_flush": 0,
      "ireq_fragmentdir": 16601,
      "ireq_fragstats": 0,
      "ireq_inodestats": 0
    },
    "mds_log": {
      "evadd": 674364896,
      "evex": 674254766,
      "evtrm": 674241715,
      "ev": 123181,
      "evexg": 0,
      "evexd": 13051,
      "segadd": 828415,
      "segex": 828260,
      "segtrm": 828242,
      "seg": 173,
      "segexg": 0,
      "segexd": 18,
      "expos": 1527961830930,
      "wrpos": 1528216562101,
      "rdpos": 0,
      "jlat": {
        "avgcount": 80478155,
        "sum": 7172726.074416821,
        "avgtime": 0.089126373
      },
      "replayed": 0
    },
    "mds_mem": {
      "ino": 1800954,
      "ino+": 1381949654,
      "ino-": 1380148700,
      "dir": 118323,
      "dir+": 76862411,
      "dir-": 76744088,
      "dn": 1831905,
      "dn+": 1515419453,
      "dn-": 1513587548,
      "cap": 150612,
      "cap+": 483620493,
      "cap-": 483469881,
      "rss": 6416116,
      "heap": 340172
    },
    "mds_server": {
      "dispatch_client_request": 1096951404,
      "dispatch_server_request": 1285638,
      "handle_client_request": 1068796009,
      "handle_client_session": 657795,
      "handle_peer_request": 2641254,
      "req_create_latency": {
        "avgcount": 66738187,
        "sum": 179066.492455464,
        "avgtime": 0.002683118
      },
      "req_getattr_latency": {
        "avgcount": 854523,
        "sum": 6004.007880271,
        "avgtime": 0.007026151
      },
      "req_getfilelock_latency": {
        "avgcount": 0,
        "sum": 0,
        "avgtime": 0
      },
      "req_link_latency": {
        "avgcount": 0,
        "sum": 0,
        "avgtime": 0
      },
      "req_lookup_latency": {
        "avgcount": 564270340,
        "sum": 2405613.05443422,
        "avgtime": 0.004263227
      },
      "req_lookuphash_latency": {
        "avgcount": 0,
        "sum": 0,
        "avgtime": 0
      },
      "req_lookupino_latency": {
        "avgcount": 69637456,
        "sum": 692870.967709712,
        "avgtime": 0.009949688
      },
      "req_lookupname_latency": {
        "avgcount": 0,
        "sum": 0,
        "avgtime": 0
      },
      "req_lookupparent_latency": {
        "avgcount": 18924826,
        "sum": 34750.757689016,
        "avgtime": 0.001836252
      },
      "req_lookupsnap_latency": {
        "avgcount": 0,
        "sum": 0,
        "avgtime": 0
      },
      "req_lssnap_latency": {
        "avgcount": 3640,
        "sum": 0.12331914,
        "avgtime": 3.3878e-05
      },
      "req_mkdir_latency": {
        "avgcount": 68041244,
        "sum": 637039.692202704,
        "avgtime": 0.009362552
      },
      "req_mknod_latency": {
        "avgcount": 0,
        "sum": 0,
        "avgtime": 0
      },
      "req_mksnap_latency": {
        "avgcount": 0,
        "sum": 0,
        "avgtime": 0
      },
      "req_open_latency": {
        "avgcount": 64540499,
        "sum": 691312.863422168,
        "avgtime": 0.010711303
      },
      "req_readdir_latency": {
        "avgcount": 8069,
        "sum": 26.479000671,
        "avgtime": 0.003281571
      },
      "req_rename_latency": {
        "avgcount": 67869252,
        "sum": 381373.466240326,
        "avgtime": 0.005619237
      },
      "req_renamesnap_latency": {
        "avgcount": 0,
        "sum": 0,
        "avgtime": 0
      },
      "req_rmdir_latency": {
        "avgcount": 67519368,
        "sum": 251275.324833405,
        "avgtime": 0.003721529
      },
      "req_rmsnap_latency": {
        "avgcount": 0,
        "sum": 0,
        "avgtime": 0
      },
      "req_rmxattr_latency": {
        "avgcount": 0,
        "sum": 0,
        "avgtime": 0
      },
      "req_setattr_latency": {
        "avgcount": 0,
        "sum": 0,
        "avgtime": 0
      },
      "req_setdirlayout_latency": {
        "avgcount": 0,
        "sum": 0,
        "avgtime": 0
      },
      "req_setfilelock_latency": {
        "avgcount": 0,
        "sum": 0,
        "avgtime": 0
      },
      "req_setlayout_latency": {
        "avgcount": 0,
        "sum": 0,
        "avgtime": 0
      },
      "req_setxattr_latency": {
        "avgcount": 70021,
        "sum": 182.147453351,
        "avgtime": 0.002601326
      },
      "req_symlink_latency": {
        "avgcount": 0,
        "sum": 0,
        "avgtime": 0
      },
      "req_unlink_latency": {
        "avgcount": 65429029,
        "sum": 164144.034317825,
        "avgtime": 0.002508734
      },
      "cap_revoke_eviction": 0,
      "cap_acquisition_throttle": 0,
      "req_getvxattr_latency": {
        "avgcount": 0,
        "sum": 0,
        "avgtime": 0
      },
      "req_addtrash_latency": {
        "avgcount": 0,
        "sum": 0,
        "avgtime": 0
      },
      "req_modtrash_latency": {
        "avgcount": 0,
        "sum": 0,
        "avgtime": 0
      },
      "req_deltrash_latency": {
        "avgcount": 0,
        "sum": 0,
        "avgtime": 0
      },
      "req_check_trash_latency": {
        "avgcount": 1096951406,
        "sum": 359.391642323,
        "avgtime": 3.27e-07
      },
      "req_get_parent_trash_latency": {
        "avgcount": 0,
        "sum": 0,
        "avgtime": 0
      }
    },
    "mds_sessions": {
      "session_count": 13,
      "session_add": 8897,
      "session_remove": 8884,
      "sessions_open": 13,
      "sessions_stale": 0,
      "total_load": 836638,
      "average_load": 64356,
      "avg_session_uptime": 756446
    },
    "mempool": {
      "bloom_filter_bytes": 1350397,
      "bloom_filter_items": 1350397,
      "bluestore_alloc_bytes": 0,
      "bluestore_alloc_items": 0,
      "bluestore_cache_data_bytes": 0,
      "bluestore_cache_data_items": 0,
      "bluestore_cache_onode_bytes": 0,
      "bluestore_cache_onode_items": 0,
      "bluestore_cache_meta_bytes": 0,
      "bluestore_cache_meta_items": 0,
      "bluestore_cache_other_bytes": 0,
      "bluestore_cache_other_items": 0,
      "bluestore_Buffer_bytes": 0,
      "bluestore_Buffer_items": 0,
      "bluestore_Extent_bytes": 0,
      "bluestore_Extent_items": 0,
      "bluestore_Blob_bytes": 0,
      "bluestore_Blob_items": 0,
      "bluestore_SharedBlob_bytes": 0,
      "bluestore_SharedBlob_items": 0,
      "bluestore_inline_bl_bytes": 0,
      "bluestore_inline_bl_items": 0,
      "bluestore_fsck_bytes": 0,
      "bluestore_fsck_items": 0,
      "bluestore_txc_bytes": 0,
      "bluestore_txc_items": 0,
      "bluestore_writing_deferred_bytes": 0,
      "bluestore_writing_deferred_items": 0,
      "bluestore_writing_bytes": 0,
      "bluestore_writing_items": 0,
      "bluefs_bytes": 0,
      "bluefs_items": 0,
      "bluefs_file_reader_bytes": 0,
      "bluefs_file_reader_items": 0,
      "bluefs_file_writer_bytes": 0,
      "bluefs_file_writer_items": 0,
      "buffer_anon_bytes": 44015685,
      "buffer_anon_items": 11057,
      "buffer_meta_bytes": 264,
      "buffer_meta_items": 3,
      "osd_bytes": 0,
      "osd_items": 0,
      "osd_mapbl_bytes": 0,
      "osd_mapbl_items": 0,
      "osd_pglog_bytes": 0,
      "osd_pglog_items": 0,
      "osdmap_bytes": 10240,
      "osdmap_items": 324,
      "osdmap_mapping_bytes": 0,
      "osdmap_mapping_items": 0,
      "pgmap_bytes": 0,
      "pgmap_items": 0,
      "mds_co_bytes": 5098617597,
      "mds_co_items": 60576033,
      "unittest_1_bytes": 0,
      "unittest_1_items": 0,
      "unittest_2_bytes": 0,
      "unittest_2_items": 0
    },
    "objecter": {
      "op_active": 0,
      "op_laggy": 0,
      "op_send": 487905324,
      "op_send_bytes": 1857513900930,
      "op_resend": 37,
      "op_reply": 487905324,
      "oplen_avg": {
        "avgcount": 487905324,
        "sum": 898082881
      },
      "op": 487905324,
      "op_r": 1107133,
      "op_w": 486798191,
      "op_rmw": 0,
      "op_pg": 0,
      "osdop_stat": 1618926,
      "osdop_create": 202873659,
      "osdop_read": 88914,
      "osdop_write": 80573423,
      "osdop_writefull": 59528,
      "osdop_writesame": 0,
      "osdop_append": 0,
      "osdop_zero": 0,
      "osdop_truncate": 6766,
      "osdop_delete": 133739043,
      "osdop_mapext": 0,
      "osdop_sparse_read": 0,
      "osdop_clonerange": 0,
      "osdop_getxattr": 177180,
      "osdop_setxattr": 405747318,
      "osdop_cmpxattr": 0,
      "osdop_rmxattr": 0,
      "osdop_resetxattrs": 0,
      "osdop_call": 0,
      "osdop_watch": 0,
      "osdop_notify": 0,
      "osdop_src_cmpxattr": 0,
      "osdop_pgls": 0,
      "osdop_pgls_filter": 0,
      "osdop_other": 0,
      "linger_active": 0,
      "linger_send": 0,
      "linger_resend": 0,
      "linger_ping": 0,
      "poolop_active": 0,
      "poolop_send": 0,
      "poolop_resend": 0,
      "poolstat_active": 0,
      "poolstat_send": 0,
      "poolstat_resend": 0,
      "statfs_active": 0,
      "statfs_send": 0,
      "statfs_resend": 0,
      "command_active": 0,
      "command_send": 0,
      "command_resend": 0,
      "map_epoch": 3100,
      "map_full": 0,
      "map_inc": 179,
      "osd_sessions": 24,
      "osd_session_open": 19165,
      "osd_session_close": 19141,
      "osd_laggy": 0,
      "omap_wr": 70451532,
      "omap_rd": 1868264,
      "omap_del": 878328
    },
    "oft": {
      "omap_total_objs": 1,
      "omap_total_kv_pairs": 12,
      "omap_total_updates": 12,
      "omap_total_removes": 0
    },
    "purge_queue": {
      "pq_executing_ops": 0,
      "pq_executing_ops_high_water": 112,
      "pq_executing": 0,
      "pq_executing_high_water": 64,
      "pq_executed": 132946557,
      "pq_item_in_journal": 0
    },
    "throttle-msgr_dispatch_throttler-mds": {
      "val": 2502,
      "max": 104857600,
      "get_started": 0,
      "get": 1723905851,
      "get_sum": 1551677135141,
      "get_or_fail_fail": 0,
      "get_or_fail_success": 1723905852,
      "take": 0,
      "take_sum": 0,
      "put": 1723905833,
      "put_sum": 1551677132386,
      "wait": {
        "avgcount": 0,
        "sum": 0,
        "avgtime": 0
      }
    },
    "throttle-objecter_bytes": {
      "val": 0,
      "max": 104857600,
      "get_started": 0,
      "get": 0,
      "get_sum": 0,
      "get_or_fail_fail": 0,
      "get_or_fail_success": 0,
      "take": 487905324,
      "take_sum": 1870926557618,
      "put": 487905324,
      "put_sum": 1870926557618,
      "wait": {
        "avgcount": 0,
        "sum": 0,
        "avgtime": 0
      }
    },
    "throttle-objecter_ops": {
      "val": 0,
      "max": 1024,
      "get_started": 0,
      "get": 0,
      "get_sum": 0,
      "get_or_fail_fail": 0,
      "get_or_fail_success": 0,
      "take": 487905324,
      "take_sum": 487905324,
      "put": 487905324,
      "put_sum": 487905324,
      "wait": {
        "avgcount": 0,
        "sum": 0,
        "avgtime": 0
      }
    },
    "throttle-write_buf_throttle": {
      "val": 0,
      "max": 3758096384,
      "get_started": 0,
      "get": 132946557,
      "get_sum": 13427603417,
      "get_or_fail_fail": 0,
      "get_or_fail_success": 132946557,
      "take": 0,
      "take_sum": 0,
      "put": 89293,
      "put_sum": 13427603417,
      "wait": {
        "avgcount": 0,
        "sum": 0,
        "avgtime": 0
      }
    },
    "throttle-write_buf_throttle-0x556fc74261a0": {
      "val": 15794,
      "max": 3758096384,
      "get_started": 0,
      "get": 674364899,
      "get_sum": 1528212373670,
      "get_or_fail_fail": 0,
      "get_or_fail_success": 674364899,
      "take": 0,
      "take_sum": 0,
      "put": 80478155,
      "put_sum": 1528212357876,
      "wait": {
        "avgcount": 0,
        "sum": 0,
        "avgtime": 0
      }
    }
  }
}
